jupyterlab_va_nb_assistant/__init__.py
jupyterlab_va_nb_assistant/_version.py
jupyterlab_va_nb_assistant/handlers.py
jupyterlab_va_nb_assistant/labextension/build_log.json
jupyterlab_va_nb_assistant/labextension/package.json
jupyterlab_va_nb_assistant/labextension/schemas/jupyterlab-va-nb-assistant/package.json.orig
jupyterlab_va_nb_assistant/labextension/schemas/jupyterlab-va-nb-assistant/plugin.json
jupyterlab_va_nb_assistant/labextension/static/lib_index_js.06f0ace06a11bdf7b638.js
jupyterlab_va_nb_assistant/labextension/static/lib_index_js.06f0ace06a11bdf7b638.js.map
jupyterlab_va_nb_assistant/labextension/static/lib_index_js.0badae34dcac587c665a.js
jupyterlab_va_nb_assistant/labextension/static/lib_index_js.0badae34dcac587c665a.js.map
jupyterlab_va_nb_assistant/labextension/static/lib_index_js.22ae597f26471cfe95ac.js
jupyterlab_va_nb_assistant/labextension/static/lib_index_js.22ae597f26471cfe95ac.js.map
jupyterlab_va_nb_assistant/labextension/static/lib_index_js.283c7545aaae4138039f.js
jupyterlab_va_nb_assistant/labextension/static/lib_index_js.283c7545aaae4138039f.js.map
jupyterlab_va_nb_assistant/labextension/static/lib_index_js.30eae9339997d61c6490.js
jupyterlab_va_nb_assistant/labextension/static/lib_index_js.30eae9339997d61c6490.js.map
jupyterlab_va_nb_assistant/labextension/static/lib_index_js.3be8851c25f7adc46f61.js
jupyterlab_va_nb_assistant/labextension/static/lib_index_js.3be8851c25f7adc46f61.js.map
jupyterlab_va_nb_assistant/labextension/static/lib_index_js.4756ec8a9d2df755fba6.js
jupyterlab_va_nb_assistant/labextension/static/lib_index_js.4756ec8a9d2df755fba6.js.map
jupyterlab_va_nb_assistant/labextension/static/lib_index_js.61ca1fd7b5f2fb91ab66.js
jupyterlab_va_nb_assistant/labextension/static/lib_index_js.61ca1fd7b5f2fb91ab66.js.map
jupyterlab_va_nb_assistant/labextension/static/lib_index_js.867aa0b4988b3055bb9f.js
jupyterlab_va_nb_assistant/labextension/static/lib_index_js.867aa0b4988b3055bb9f.js.map
jupyterlab_va_nb_assistant-0.2.0.dist-info/METADATA
jupyterlab_va_nb_assistant-0.2.0.dist-info/WHEEL
jupyterlab_va_nb_assistant-0.2.0.dist-info/licenses/LICENSE
jupyterlab_va_nb_assistant-0.2.0.dist-info/RECORD
